MANIFEST.in
README.rst
setup.py
docs/HISTORY.txt
docs/INSTALL.txt
docs/LICENSE.GPL
docs/LICENSE.txt
redturtle/__init__.py
redturtle.portlet.content.egg-info/PKG-INFO
redturtle.portlet.content.egg-info/SOURCES.txt
redturtle.portlet.content.egg-info/dependency_links.txt
redturtle.portlet.content.egg-info/entry_points.txt
redturtle.portlet.content.egg-info/namespace_packages.txt
redturtle.portlet.content.egg-info/not-zip-safe
redturtle.portlet.content.egg-info/requires.txt
redturtle.portlet.content.egg-info/top_level.txt
redturtle/portlet/__init__.py
redturtle/portlet/content/__init__.py
redturtle/portlet/content/configure.zcml
redturtle/portlet/content/contentportlet.pt
redturtle/portlet/content/contentportlet.py
redturtle/portlet/content/i18n.sh
redturtle/portlet/content/vocabulary.py
redturtle/portlet/content/browser/__init__.py
redturtle/portlet/content/browser/configure.zcml
redturtle/portlet/content/browser/stylesheets/content.css
redturtle/portlet/content/i18n/plone-it.po
redturtle/portlet/content/locales/manual.pot
redturtle/portlet/content/locales/redturtle.portlet.content.pot
redturtle/portlet/content/locales/it/LC_MESSAGES/redturtle.portlet.content.mo
redturtle/portlet/content/locales/it/LC_MESSAGES/redturtle.portlet.content.po
redturtle/portlet/content/profiles/default/cssregistry.xml
redturtle/portlet/content/profiles/default/metadata.xml
redturtle/portlet/content/profiles/default/portlets.xml
redturtle/portlet/content/tests/__init__.py
redturtle/portlet/content/tests/base.py
redturtle/portlet/content/tests/test_portlet.py