Metadata-Version: 1.0
Name: redturtle.portlet.content
Version: 1.4.1
Summary: A generic portlet that allows to show various parts of a document, like title, description, text, image and comments.
Home-page: http://plone.org/products/redturtle.portlet.content
Author: RedTurtle Technology
Author-email: sviluppoplone@redturtle.it
License: GPL
Keywords: portlet content generic
Platform: UNKNOWN
Classifier: Framework :: Plone
Classifier: Framework :: Plone :: 3.3
Classifier: Framework :: Plone :: 4.0
Classifier: Framework :: Plone :: 4.1
Classifier: Framework :: Plone :: 4.2
Classifier: Framework :: Plone :: 4.3
Classifier: Programming Language :: Python
Classifier: Topic :: Software Development :: Libraries :: Python Modules
